emsarray_smc.py
emsarray_smc-0.5.0.dist-info/licenses/LICENCE
emsarray_smc-0.5.0.dist-info/METADATA
emsarray_smc-0.5.0.dist-info/WHEEL
emsarray_smc-0.5.0.dist-info/entry_points.txt
emsarray_smc-0.5.0.dist-info/top_level.txt
emsarray_smc-0.5.0.dist-info/RECORD
