Metadata-Version: 2.4
Name: emsarray_smc
Version: 0.5.0
Summary: Support for spherical multiple-cell geometry in emsarray
Author-email: "Coastal Environmental Modelling team, Oceans and Atmosphere, CSIRO" <coasts@csiro.au>
License-Expression: BSD-3-Clause
Project-URL: Source, https://github.com/csiro-coasts/emsarray-smc/
License-File: LICENCE
Requires-Dist: emsarray>=0.8.0
Provides-Extra: testing
Requires-Dist: pytest; extra == "testing"
Dynamic: license-file
